corenlp_client/__corenlp_client.py
corenlp_client/__init__.py
corenlp_client-1.0.6.dist-info/LICENSE
corenlp_client-1.0.6.dist-info/METADATA
corenlp_client-1.0.6.dist-info/WHEEL
corenlp_client-1.0.6.dist-info/top_level.txt
corenlp_client-1.0.6.dist-info/RECORD
