Metadata-Version: 2.1
Name: corenlp-client
Version: 1.0.6
Summary: A python wapper for Stanford CoreNLP, simple and customizable. 
Home-page: https://github.com/Jason3900/corenlp_client
Author: Jason Fang
Author-email: jasonfang3900@gmail.com
License: UNKNOWN
Platform: UNKNOWN
Classifier: Programming Language :: Python :: 3
Classifier: License :: OSI Approved :: MIT License
Classifier: Operating System :: OS Independent
Requires-Python: >=3.6
Requires-Dist: nltk
Requires-Dist: requests
